[{"pitch": "a_2", "rect": [85, 489, 139, 639], "duration": "a_0"}, {"pitch": "a_1", "rect": [142, 489, 196, 639], "duration": "a_0"}, {"pitch": "a_0", "rect": [199, 489, 253, 639], "duration": "a_0"}, {"pitch": "a_1", "rect": [255, 489, 309, 639], "duration": "a_0"}, {"pitch": "a_2", "rect": [336, 489, 390, 639], "duration": "a_0"}, {"pitch": "a_2", "rect": [393, 489, 447, 639], "duration": "a_0"}, {"pitch": "a_2", "rect": [451, 489, 505, 639], "duration": "a_1"}, {"pitch": "a_1", "rect": [555, 489, 609, 639], "duration": "a_0"}, {"pitch": "a_1", "rect": [612, 489, 666, 639], "duration": "a_0"}, {"pitch": "a_1", "rect": [670, 489, 724, 639], "duration": "a_1"}, {"pitch": "a_2", "rect": [773, 489, 827, 639], "duration": "a_0"}, {"pitch": "a_3", "rect": [833, 489, 887, 639], "duration": "a_0"}, {"pitch": "a_3", "rect": [890, 489, 944, 639], "duration": "a_1"}, {"pitch": "a_2", "rect": [992, 489, 1046, 639], "duration": "a_0"}, {"pitch": "a_1", "rect": [1047, 489, 1101, 639], "duration": "a_0"}, {"pitch": "a_0", "rect": [1103, 489, 1157, 639], "duration": "a_0"}, {"pitch": "a_1", "rect": [1158, 489, 1212, 639], "duration": "a_0"}, {"pitch": "a_2", "rect": [1237, 489, 1291, 639], "duration": "a_0"}, {"pitch": "a_2", "rect": [1293, 489, 1347, 639], "duration": "a_0"}, {"pitch": "a_2", "rect": [1348, 489, 1402, 639], "duration": "a_0"}, {"pitch": "a_2", "rect": [1404, 489, 1458, 639], "duration": "a_0"}, {"pitch": "a_1", "rect": [1482, 489, 1536, 639], "duration": "a_0"}, {"pitch": "a_1", "rect": [1537, 489, 1591, 639], "duration": "a_0"}, {"pitch": "a_2", "rect": [1591, 489, 1645, 639], "duration": "a_0"}, {"pitch": "a_1", "rect": [1645, 489, 1699, 639], "duration": "a_0"}, {"pitch": "a_0", "rect": [1729, 489, 1783, 639], "duration": "a_2"}]
